testloop/__init__.py
testloop/testloop.py
testloop-0.1.1.dist-info/entry_points.txt
testloop-0.1.1.dist-info/LICENSE
testloop-0.1.1.dist-info/WHEEL
testloop-0.1.1.dist-info/METADATA
testloop-0.1.1.dist-info/RECORD
