Metadata-Version: 2.1
Name: testloop
Version: 0.1.1
Summary: A nimble testing tool
Home-page: https://github.com/jskulski/testloop
Author: Jon Skulski
Author-email: jskulski@gmail.com
Requires-Python: >=3.11,<4.0
Classifier: Programming Language :: Python :: 3
Classifier: Programming Language :: Python :: 3.11
Project-URL: Repository, https://github.com/jskulski/testloop
